data7/.secrets.yaml.dist
data7/__init__.py
data7/__main__.py
data7/app.py
data7/cli.py
data7/config.py
data7/data7.yaml.dist
data7/models.py
data7/settings.yaml.dist
data7/streamers.py
data7/utils.py
data7-1.0.1.dist-info/METADATA
data7-1.0.1.dist-info/WHEEL
data7-1.0.1.dist-info/entry_points.txt
data7-1.0.1.dist-info/licenses/LICENSE
data7-1.0.1.dist-info/RECORD
