Metadata-Version: 2.4
Name: data7
Version: 1.0.1
Summary: Data7 streams CSV/Parquet datasets over HTTP from SQL queries.
Project-URL: Homepage, https://jmaupetit.github.io/data7/
Project-URL: Repository, https://github.com/jmaupetit/data7
Project-URL: Documentation, https://jmaupetit.github.io/data7/
Author-email: Julien Maupetit <julien@maupetit.net>
License-Expression: MIT
License-File: LICENSE
Keywords: CSV,HTTP,Parquet,SQL,database,dataset
Classifier: Development Status :: 5 - Production/Stable
Classifier: Topic :: Database
Classifier: Topic :: Internet :: WWW/HTTP :: WSGI
Requires-Python: >=3.11
Requires-Dist: dynaconf>=3
Requires-Dist: pandas>=2
Requires-Dist: pyarrow>=20
Requires-Dist: pyinstrument>=5
Requires-Dist: sentry-sdk[starlette]>=2
Requires-Dist: sqlalchemy>=2
Requires-Dist: starlette>=0.1
Requires-Dist: typer>=0.1
Requires-Dist: uvicorn[standard]>=0.1
